LICENSE.txt
README.md
epubfile.py
setup.py
epubfile.egg-info/PKG-INFO
epubfile.egg-info/SOURCES.txt
epubfile.egg-info/dependency_links.txt
epubfile.egg-info/requires.txt
epubfile.egg-info/top_level.txt