Metadata-Version: 2.1
Name: epubfile
Version: 0.0.8
Summary: simple epub file reading and writing
Home-page: https://github.com/voussoir/epubfile
Author: voussoir
Author-email: pypi@voussoir.net
License: UNKNOWN
Platform: UNKNOWN
